{
  "publicReadable": true,
  "publicWritable": false,
  "useQueryParamTargetingClientSide": false,
  "showAbTests": true,
  "id": "37e2bb9c9af7414b83a142c792be2485",
  "strictPrivateRead": false,
  "name": "product-page",
  "webhooks": [],
  "allowTests": true,
  "showMetrics": true,
  "hooks": {},
  "individualEmbed": false,
  "subType": "",
  "allowMetrics": true,
  "kind": "component",
  "isPage": false,
  "lastUpdateBy": null,
  "injectWcPosition": "",
  "showScheduling": true,
  "showTargeting": true,
  "allowHeatmap": true,
  "hideOptions": false,
  "singleton": false,
  "bigData": false,
  "defaultQuery": [],
  "autoTracked": true,
  "injectWcAt": "",
  "hidden": false,
  "sendToElasticSearch": false,
  "helperText": "",
  "schema": {},
  "pathPrefix": "/",
  "fields": [
    {
      "noPhotoPicker": false,
      "@type": "@builder.io/core:Field",
      "advanced": false,
      "model": "",
      "disallowRemove": false,
      "name": "blocks",
      "helperText": "",
      "mandatory": false,
      "copyOnAdd": true,
      "permissionsRequiredToEdit": "",
      "required": true,
      "showIf": "",
      "autoFocus": false,
      "showTemplatePicker": true,
      "hideFromFieldsEditor": true,
      "type": "uiBlocks",
      "hideFromUI": false,
      "onChange": "",
      "simpleTextOnly": false,
      "hidden": false,
      "subFields": []
    },
    {
      "defaultValue": {
        "@type": "@builder.io/core:Request",
        "request": {
          "url": "https://cdn.builder.io/api/v1/shopify/products/{{this.options.product}}.json?apiKey=6d39f4449e2b4e6792a793bb8c1d9615",
          "method": "GET"
        },
        "options": {
          "product": 6206263525555
        }
      },
      "disallowRemove": false,
      "permissionsRequiredToEdit": "",
      "hideFromUI": false,
      "autoFocus": false,
      "simpleTextOnly": false,
      "@type": "@builder.io/core:Field",
      "subFields": [],
      "required": false,
      "mandatory": false,
      "showTemplatePicker": true,
      "showIf": "",
      "name": "productPreview",
      "copyOnAdd": true,
      "advanced": false,
      "noPhotoPicker": false,
      "hidden": false,
      "hideFromFieldsEditor": false,
      "type": "ShopifyProductPreview",
      "model": "",
      "onChange": "",
      "helperText": ""
    }
  ],
  "getSchemaFromPage": false,
  "sendToMongoDb": true,
  "examplePageUrl": "${space.siteUrl}/product/${previewProduct.handle}",
  "requiredTargets": [],
  "designerVersion": 1,
  "componentsOnlyMode": false,
  "strictPrivateWrite": false,
  "hideFromUI": false,
  "archived": false,
  "repeatable": false,
  "@originId": "7c834559dcc183dd381b13ae41cd7bd325ecceba05de9f24b61fd3428c583fc9"
}